EchoAPI/Client.py
EchoAPI/Message.py
EchoAPI/User.py
EchoAPI/__init__.py
EchoAPI/common.py
EchoAPI/event.py
EchoAPI/exceptions.py
EchoMessagerAPI-0.0.8.dist-info/LICENSE
EchoMessagerAPI-0.0.8.dist-info/METADATA
EchoMessagerAPI-0.0.8.dist-info/WHEEL
EchoMessagerAPI-0.0.8.dist-info/top_level.txt
EchoMessagerAPI-0.0.8.dist-info/RECORD
